timecalc.py
gnsstoolbox_timecalc-0.1.2.dist-info/METADATA
gnsstoolbox_timecalc-0.1.2.dist-info/WHEEL
gnsstoolbox_timecalc-0.1.2.dist-info/entry_points.txt
gnsstoolbox_timecalc-0.1.2.dist-info/top_level.txt
gnsstoolbox_timecalc-0.1.2.dist-info/RECORD
