Metadata-Version: 2.2
Name: gnsstoolbox-timecalc
Version: 0.1.2
Summary: CLI tool for converting UTC to GPS Time
Author-email: Jared Wilson <jared.t.wilson@gmail.com>
Project-URL: Homepage, https://github.com/jaredw42/gnsstoolbox
Project-URL: Issues, https://github.com/jaredw42/gnsstoolbox/issues
Classifier: Programming Language :: Python :: 3
Classifier: Operating System :: OS Independent
Requires-Python: >=3.8
